pyciclib/__init__.py
pyciclib/core.py
pyciclib-0.2.0.dist-info/licenses/LICENSE
pyciclib-0.2.0.dist-info/METADATA
pyciclib-0.2.0.dist-info/WHEEL
pyciclib-0.2.0.dist-info/top_level.txt
pyciclib-0.2.0.dist-info/RECORD
