Metadata-Version: 2.4
Name: pyciclib
Version: 0.2.0
Summary: A flexible compound interest calculator.
Author-email: Fabian Bauer <fab.bauer@outlook.com>
License-Expression: GPL-3.0-or-later
Project-URL: Homepage, https://github.com/Fab2102/pyciclib
Project-URL: Documentation, https://github.com/Fab2102/pyciclib#readme
Project-URL: Source, https://github.com/Fab2102/pyciclib
Project-URL: Tracker, https://github.com/Fab2102/pyciclib/issues
Keywords: finance,compound interest,investment,calculator
Classifier: Development Status :: 4 - Beta
Classifier: Intended Audience :: Developers
Classifier: Programming Language :: Python :: 3
Classifier: Programming Language :: Python :: 3.10
Classifier: Programming Language :: Python :: 3.11
Classifier: Programming Language :: Python :: 3.12
Classifier: Topic :: Office/Business :: Financial
Requires-Python: >=3.10
License-File: LICENSE
Requires-Dist: pandas<3.0,>=2.0
Provides-Extra: dev
Requires-Dist: pytest; extra == "dev"
Dynamic: license-file
